[
    {
        "xtf_id": "facility_BEG",
        "name": "Berg",
        "operator": "Technische Gemeindebetriebe Elektra",
        "website": "http://www.berg-tg.ch",
        "type": "facilityType_small",
        "operationalStatus": "operationalStatus_normalbetrieb",
        "ratedPower": "6.5",
        "x": "2731128.8418347235",
        "y": "1271648.5450638824"
    },
    {
        "xtf_id": "facility_BER",
        "name": "Beringen SH",
        "operator": "\"EKS AG",
        "website": " Schaffhausen\"",
        "type": "",
        "operationalStatus": "facilityType_small",
        "ratedPower": "operationalStatus_stillgelegt",
        "x": "3.0",
        "y": "2685501.143304388"
    },
    {
        "xtf_id": "facility_BRU",
        "name": "Brütten 2",
        "operator": "Urs Arter",
        "website": "",
        "type": "facilityType_small",
        "operationalStatus": "operationalStatus_normalbetrieb",
        "ratedPower": "6.5",
        "x": "2692040.9764632857",
        "y": "1259078.8337028702"
    },
    {
        "xtf_id": "facility_CHU",
        "name": "Chürstein (Gäbris)",
        "operator": "Appenzell. Ver. zur Förderung umweltfreundl. En.",
        "website": "http://www.appenzeller-energie.ch",
        "type": "facilityType_small",
        "operationalStatus": "operationalStatus_normalbetrieb",
        "ratedPower": "80.0",
        "x": "2753193.540256478",
        "y": "1250437.6384445291"
    },
    {
        "xtf_id": "facility_COL",
        "name": "Collonges",
        "operator": "RhônEole SA",
        "website": "http://www.rhoneole.ch",
        "type": "facilityType_big",
        "operationalStatus": "operationalStatus_normalbetrieb",
        "ratedPower": "2000.0",
        "x": "2568999.350192574",
        "y": "1112120.260908145"
    },
    {
        "xtf_id": "facility_CTI",
        "name": "Chli Titlis",
        "operator": "Elektrizitätswerk Nidwalden",
        "website": "",
        "type": "facilityType_small",
        "operationalStatus": "operationalStatus_stillgelegt",
        "ratedPower": "30.0",
        "x": "2675100.57105117",
        "y": "1180479.7692706678"
    },
    {
        "xtf_id": "facility_DIE",
        "name": "Diegenstal",
        "operator": "Genossenschaft Windenergieanlage Diegenstal",
        "website": "http://www.bauer-fritz.ch",
        "type": "facilityType_small",
        "operationalStatus": "operationalStatus_normalbetrieb",
        "ratedPower": "30.0",
        "x": "2653290.7224926897",
        "y": "1227578.1016170552"
    },
    {
        "xtf_id": "facility_FEL",
        "name": "Feldmoos/Rengg",
        "operator": "WindPower AG",
        "website": "",
        "type": "facilityType_windpark",
        "operationalStatus": "operationalStatus_normalbetrieb",
        "ratedPower": "1850.0",
        "x": "2649313.62256124",
        "y": "1204521.9661266939"
    },
    {
        "xtf_id": "facility_GUE",
        "name": "Gütsch",
        "operator": "EW Ursern",
        "website": "http://www.ew-ursern.ch/Windkraft.10.0.html",
        "type": "facilityType_windpark",
        "operationalStatus": "operationalStatus_normalbetrieb",
        "ratedPower": "3300.0",
        "x": "2690145.420818921",
        "y": "1167674.6302455517"
    },
    {
        "xtf_id": "facility_HET",
        "name": "Hettlingen ZH",
        "operator": "Genossenschaft SolVent",
        "website": "",
        "type": "facilityType_small",
        "operationalStatus": "operationalStatus_stillgelegt",
        "ratedPower": "2.0",
        "x": "2695001.0097399456",
        "y": "1265659.7941228584"
    },
    {
        "xtf_id": "facility_ALP",
        "name": "Alpboden-Haldigrat",
        "operator": "Haldigrat AG",
        "website": "",
        "type": "facilityType_small",
        "operationalStatus": "operationalStatus_normalbetrieb",
        "ratedPower": "20.0",
        "x": "2675813.70130236",
        "y": "1193420.769778985"
    },
    {
        "xtf_id": "facility_HOR",
        "name": "Horn",
        "operator": "Envergate Energy AG",
        "website": "",
        "type": "facilityType_small",
        "operationalStatus": "operationalStatus_normalbetrieb",
        "ratedPower": "15.0",
        "x": "2753069.6310384087",
        "y": "1262143.5424160305"
    },
    {
        "xtf_id": "facility_SUP",
        "name": "Schüpfheim",
        "operator": "Kantonsschule Schüpfheim",
        "website": "",
        "type": "facilityType_small",
        "operationalStatus": "operationalStatus_normalbetrieb",
        "ratedPower": "10.0",
        "x": "2644347.545150123",
        "y": "1200631.9542539993"
    },
    {
        "xtf_id": "facility_LCV",
        "name": "Le Cerneux-Veusil",
        "operator": "\"Jura Energie",
        "website": " Jean Oppliger Sŕrl\"",
        "type": "http://www.jura-energie.ch",
        "operationalStatus": "facilityType_small",
        "ratedPower": "operationalStatus_normalbetrieb",
        "x": "6.5",
        "y": "2562625.0835047713"
    },
    {
        "xtf_id": "facility_LFE",
        "name": "La Ferričre",
        "operator": "\"Jura Energie",
        "website": " Jean Oppliger Sŕrl\"",
        "type": "http://www.jura-energie.ch",
        "operationalStatus": "facilityType_small",
        "ratedPower": "operationalStatus_normalbetrieb",
        "x": "6.5",
        "y": "2562521.0339249973"
    },
    {
        "xtf_id": "facility_MAR",
        "name": "Marthalen",
        "operator": "Genosol Martella",
        "website": "http://www.genosol.ch",
        "type": "facilityType_small",
        "operationalStatus": "operationalStatus_normalbetrieb",
        "ratedPower": "6.5",
        "x": "2691455.134620456",
        "y": "1276802.7621499912"
    },
    {
        "xtf_id": "facility_MTC",
        "name": "Mt. Crosin",
        "operator": "JUVENT SA",
        "website": "http://www.juvent.ch",
        "type": "facilityType_windpark",
        "operationalStatus": "operationalStatus_normalbetrieb",
        "ratedPower": "37200.0",
        "x": "2567900.1449172385",
        "y": "1225300.7045913136"
    },
    {
        "xtf_id": "facility_OGR",
        "name": "Oberer Grenchenberg",
        "operator": "ADEV Windkraft AG",
        "website": "http://www.adev.ch/",
        "type": "facilityType_medium",
        "operationalStatus": "operationalStatus_normalbetrieb",
        "ratedPower": "150.0",
        "x": "2597100.369715936",
        "y": "1231260.4122750135"
    },
    {
        "xtf_id": "facility_RUT",
        "name": "Rüttenen",
        "operator": "Toni Marti",
        "website": "",
        "type": "facilityType_small",
        "operationalStatus": "operationalStatus_normalbetrieb",
        "ratedPower": "6.5",
        "x": "2607190.3078911337",
        "y": "1232287.3550700704"
    },
    {
        "xtf_id": "facility_SCH",
        "name": "Schaber Emmental",
        "operator": "Lukas Meister",
        "website": "http://www.clevergie.ch/portfolio/wyssachenbe/",
        "type": "facilityType_small",
        "operationalStatus": "operationalStatus_normalbetrieb",
        "ratedPower": "15.0",
        "x": "2627581.4240166685",
        "y": "1212076.0877252207"
    },
    {
        "xtf_id": "facility_HOC",
        "name": "Hochstuckli",
        "operator": "Envergate Energy AG",
        "website": "",
        "type": "facilityType_small",
        "operationalStatus": "operationalStatus_stillgelegt",
        "ratedPower": "10.0",
        "x": "2693357.700447049",
        "y": "1213799.8217599003"
    },
    {
        "xtf_id": "facility_SIM",
        "name": "Simplon Passhöhe",
        "operator": "jetstream Sempione GmbH",
        "website": "",
        "type": "facilityType_small",
        "operationalStatus": "operationalStatus_stillgelegt",
        "ratedPower": "30.0",
        "x": "2645089.700185784",
        "y": "1121879.6204336414"
    },
    {
        "xtf_id": "facility_SOO",
        "name": "\"Sool",
        "operator": " Langenbruck\"",
        "website": "Ökozentrum Langenbruck",
        "type": "",
        "operationalStatus": "facilityType_small",
        "ratedPower": "operationalStatus_normalbetrieb",
        "x": "28.0",
        "y": "2622165.504977952"
    },
    {
        "xtf_id": "facility_STM",
        "name": "St. Moritz",
        "operator": "Aventa",
        "website": "",
        "type": "facilityType_small",
        "operationalStatus": "operationalStatus_stillgelegt",
        "ratedPower": "6.5",
        "x": "2781350.9588127127",
        "y": "1152949.6468857261"
    },
    {
        "xtf_id": "facility_SWM",
        "name": "Schwengimatt",
        "operator": "Nicole und Jürg Lehmann",
        "website": "http://www.schwengimatt.ch",
        "type": "facilityType_small",
        "operationalStatus": "operationalStatus_normalbetrieb",
        "ratedPower": "6.5",
        "x": "2618438.445676604",
        "y": "1238295.2810145586"
    },
    {
        "xtf_id": "facility_TRA",
        "name": "Tramelan",
        "operator": "\"Jura Energie",
        "website": " Jean Oppliger Sŕrl\"",
        "type": "http://www.jura-energie.ch",
        "operationalStatus": "facilityType_small",
        "ratedPower": "operationalStatus_normalbetrieb",
        "x": "6.5",
        "y": "2575433.23388892"
    },
    {
        "xtf_id": "facility_WIT",
        "name": "Winterthur Taggenberg 1 und 2",
        "operator": "Aventa",
        "website": "",
        "type": "facilityType_small",
        "operationalStatus": "operationalStatus_normalbetrieb",
        "ratedPower": "13.0",
        "x": "2695648.0089056287",
        "y": "1263995.7940148076"
    },
    {
        "xtf_id": "facility_WIW",
        "name": "Winterthur Wiesendangerstrasse",
        "operator": "Aventa",
        "website": "",
        "type": "facilityType_small",
        "operationalStatus": "operationalStatus_normalbetrieb",
        "ratedPower": "6.5",
        "x": "2699991.943403035",
        "y": "1265435.742787773"
    },
    {
        "xtf_id": "facility_BRT",
        "name": "Brütten 1",
        "operator": "GS Engineering / Walter Büchi",
        "website": "",
        "type": "facilityType_small",
        "operationalStatus": "operationalStatus_normalbetrieb",
        "ratedPower": "6.5",
        "x": "2694097.966567842",
        "y": "1259056.8219030607"
    },
    {
        "xtf_id": "facility_LAJ",
        "name": "Lajoux",
        "operator": "Jčrôme Willemin",
        "website": "",
        "type": "facilityType_small",
        "operationalStatus": "operationalStatus_normalbetrieb",
        "ratedPower": "13.0",
        "x": "2578606.28494302",
        "y": "1237566.5636612952"
    },
    {
        "xtf_id": "facility_STB",
        "name": "St. Brais",
        "operator": "ADEV Windkraft AG",
        "website": "http://www.adev.ch/",
        "type": "facilityType_windpark",
        "operationalStatus": "operationalStatus_normalbetrieb",
        "ratedPower": "4000.0",
        "x": "2574690.283180896",
        "y": "1239200.6008802103"
    },
    {
        "xtf_id": "facility_MTG",
        "name": "Martigny",
        "operator": "RhônEole SA",
        "website": "http://www.rhoneole.ch",
        "type": "facilityType_big",
        "operationalStatus": "operationalStatus_normalbetrieb",
        "ratedPower": "2050.0",
        "x": "2570138.2222330663",
        "y": "1108435.2068784935"
    },
    {
        "xtf_id": "facility_FEU",
        "name": "Feusisberg",
        "operator": "Envergate Energy AG",
        "website": "",
        "type": "facilityType_small",
        "operationalStatus": "operationalStatus_normalbetrieb",
        "ratedPower": "15.0",
        "x": "2698124.792701188",
        "y": "1226405.856632872"
    },
    {
        "xtf_id": "facility_PEU",
        "name": "Peuchapatte",
        "operator": "Eole Jura SA",
        "website": "http://www.alpiq.ch",
        "type": "facilityType_windpark",
        "operationalStatus": "operationalStatus_normalbetrieb",
        "ratedPower": "6900.0",
        "x": "2563955.1162895174",
        "y": "1228024.7561306017"
    },
    {
        "xtf_id": "facility_VIL",
        "name": "Vilters",
        "operator": "Bernhard Wälti",
        "website": "",
        "type": "facilityType_small",
        "operationalStatus": "operationalStatus_normalbetrieb",
        "ratedPower": "6.5",
        "x": "2755274.693742405",
        "y": "1211501.7707129356"
    },
    {
        "xtf_id": "facility_GRI",
        "name": "Gries",
        "operator": "GriesWind AG",
        "website": "http://www.swisswinds.com",
        "type": "facilityType_windpark",
        "operationalStatus": "operationalStatus_normalbetrieb",
        "ratedPower": "9360.0",
        "x": "2671977.0874390407",
        "y": "1146165.6913124993"
    },
    {
        "xtf_id": "facility_CHA",
        "name": "\"Charrat VS",
        "operator": " Adonis\"",
        "website": "ValEole SA",
        "type": "http://www.valeole.ch",
        "operationalStatus": "facilityType_big",
        "ratedPower": "operationalStatus_normalbetrieb",
        "x": "3000.0",
        "y": "2577337.280352426"
    },
    {
        "xtf_id": "facility_SCR",
        "name": "Schmiedrued",
        "operator": "Anton Suter",
        "website": "",
        "type": "facilityType_small",
        "operationalStatus": "operationalStatus_normalbetrieb",
        "ratedPower": "10.0",
        "x": "2649247.725935968",
        "y": "1234858.0945704202"
    },
    {
        "xtf_id": "facility_HAL",
        "name": "Haldenstein",
        "operator": "Calandawind",
        "website": "http://www.calandawind.ch",
        "type": "facilityType_big",
        "operationalStatus": "operationalStatus_normalbetrieb",
        "ratedPower": "3000.0",
        "x": "2760010.8453908064",
        "y": "1195797.632248905"
    },
    {
        "xtf_id": "facility_LUT",
        "name": "Lutersarni",
        "operator": "Centralschweizerische Kraftwerke AG (CKW)",
        "website": "http://www.ckw.ch",
        "type": "facilityType_big",
        "operationalStatus": "operationalStatus_normalbetrieb",
        "ratedPower": "2300.0",
        "x": "2650922.6542131216",
        "y": "1205069.977662904"
    },
    {
        "xtf_id": "facility_GOL",
        "name": "Goldau",
        "operator": "Wind Energie Goldau AG",
        "website": "",
        "type": "facilityType_small",
        "operationalStatus": "operationalStatus_normalbetrieb",
        "ratedPower": "20.0",
        "x": "2684900.6382414126",
        "y": "1210599.78574202"
    },
    {
        "xtf_id": "facility_ALL",
        "name": "Allenwinden",
        "operator": "Bernhard Wälti",
        "website": "",
        "type": "facilityType_small",
        "operationalStatus": "operationalStatus_normalbetrieb",
        "ratedPower": "6.5",
        "x": "2689589.1429695077",
        "y": "1282466.6848064533"
    },
    {
        "xtf_id": "facility_LOT",
        "name": "Lötschenpass",
        "operator": "Beat Dietrich",
        "website": "https://www.loetschenpass.ch/",
        "type": "facilityType_small",
        "operationalStatus": "operationalStatus_normalbetrieb",
        "ratedPower": "5.0",
        "x": "2621333.681788503",
        "y": "1140523.9446979216"
    },
    {
        "xtf_id": "facility_GOT",
        "name": "San Gottardo",
        "operator": "Azienda Elettrica Ticinese",
        "website": "https://www.aet.ch",
        "type": "facilityType_windpark",
        "operationalStatus": "operationalStatus_normalbetrieb",
        "ratedPower": "11750.0",
        "x": "2685943.315653926",
        "y": "1156992.6902073394"
    },
    {
        "xtf_id": ""
    }
]